aioapp_amqp/__init__.py
tests/__init__.py
tests/conftest.py
tests/docker-compose.yml
tests/test_amqp.py
aioapp_amqp-0.0.1b3.dist-info/AUTHORS.rst
aioapp_amqp-0.0.1b3.dist-info/LICENSE
aioapp_amqp-0.0.1b3.dist-info/METADATA
aioapp_amqp-0.0.1b3.dist-info/WHEEL
aioapp_amqp-0.0.1b3.dist-info/top_level.txt
aioapp_amqp-0.0.1b3.dist-info/RECORD
